found/__init__.py
found/base.py
found/bstore.py
found/eavstore.py
found/fdb_c.h
found/fdb_c2.h
found/ffibuild.py
found/index.html
found/nstore.py
found/pool.py
found/pstore.py
found/templates/history-change.html
found/templates/history-detail-add.html
found/templates/history-detail-apply.html
found/templates/history-detail-remove.html
found/templates/history-detail.html
found/templates/history-list.html
found/templates/index.html
found/templates/navigate.html
found/tests.py
found/vnstore.py
asyncio_foundationdb-0.12.0.dist-info/LICENSE
asyncio_foundationdb-0.12.0.dist-info/METADATA
asyncio_foundationdb-0.12.0.dist-info/WHEEL
asyncio_foundationdb-0.12.0.dist-info/RECORD
