Metadata-Version: 2.1
Name: asyncio-foundationdb
Version: 0.12.0
Summary: FoundationDB drivers for asyncio
License: Apache v2
Author: ⵄⵎⵉⵔⵓⵛ ⴰⵎⴰⵣⵉⵖ
Author-email: amirouche@hyper.dev
Requires-Python: >=3.8,<4.0
Classifier: License :: Other/Proprietary License
Classifier: Programming Language :: Python :: 3
Classifier: Programming Language :: Python :: 3.8
Classifier: Programming Language :: Python :: 3.9
Classifier: Programming Language :: Python :: 3.10
Classifier: Programming Language :: Python :: 3.11
Classifier: Programming Language :: Python :: 3.12
Requires-Dist: aiostream (>=0.5,<0.6)
Requires-Dist: cffi (>=1,<2)
Requires-Dist: foundationdb (>=7.3,<8.0)
Requires-Dist: immutables (>=0,<1)
Requires-Dist: jinja2 (>=3,<4)
Requires-Dist: loguru (>=0,<1)
Requires-Dist: more-itertools (>=10,<11)
Requires-Dist: uuid7 (>=0.1,<0.2)
Requires-Dist: uvicorn (>=0.24,<0.25)
Requires-Dist: zstandard (>=0.22,<0.23)
